[{"fips":"8001","total_vote":"193677","clinton":"96558","trump":"80082"},{"fips":"8003","total_vote":"6939","clinton":"3189","trump":"3046"},{"fips":"8005","total_vote":"303048","clinton":"159885","trump":"117053"},{"fips":"8007","total_vote":"7339","clinton":"2500","trump":"4264"},{"fips":"8009","total_vote":"2153","clinton":"283","trump":"1753"},{"fips":"8011","total_vote":"1927","clinton":"590","trump":"1188"},{"fips":"8013","total_vote":"188145","clinton":"132334","trump":"41396"},{"fips":"8014","total_vote":"37690","clinton":"19731","trump":"14367"},{"fips":"8015","total_vote":"11250","clinton":"4888","trump":"5391"},{"fips":"8017","total_vote":"1102","clinton":"132","trump":"925"},{"fips":"8019","total_vote":"5866","clinton":"2729","trump":"2575"},{"fips":"8021","total_vote":"4022","clinton":"1771","trump":"1914"},{"fips":"8023","total_vote":"1848","clinton":"1125","trump":"588"},{"fips":"8025","total_vote":"1527","clinton":"339","trump":"1079"},{"fips":"8027","total_vote":"3066","clinton":"797","trump":"2061"},{"fips":"8029","total_vote":"16790","clinton":"4087","trump":"11655"},{"fips":"8031","total_vote":"331852","clinton":"244551","trump":"62690"},{"fips":"8033","total_vote":"1255","clinton":"242","trump":"944"},{"fips":"8035","total_vote":"187500","clinton":"68657","trump":"102573"},{"fips":"8037","total_vote":"25223","clinton":"14099","trump":"8990"},{"fips":"8039","total_vote":"15980","clinton":"3134","trump":"11705"},{"fips":"8041","total_vote":"318968","clinton":"108010","trump":"179228"},{"fips":"8043","total_vote":"21973","clinton":"5297","trump":"15122"},{"fips":"8045","total_vote":"26470","clinton":"11271","trump":"13132"},{"fips":"8047","total_vote":"3576","clinton":"1634","trump":"1566"},{"fips":"8049","total_vote":"8588","clinton":"3358","trump":"4494"},{"fips":"8051","total_vote":"9412","clinton":"5128","trump":"3289"},{"fips":"8053","total_vote":"589","clinton":"197","trump":"339"},{"fips":"8055","total_vote":"3783","clinton":"1633","trump":"1883"},{"fips":"8057","total_vote":"861","clinton":"171","trump":"629"},{"fips":"8059","total_vote":"328883","clinton":"160776","trump":"138177"},{"fips":"8061","total_vote":"855","clinton":"91","trump":"728"},{"fips":"8063","total_vote":"3702","clinton":"536","trump":"2967"},{"fips":"8065","total_vote":"3199","clinton":"1616","trump":"1270"},{"fips":"8067","total_vote":"31150","clinton":"15525","trump":"12587"},{"fips":"8069","total_vote":"195981","clinton":"93113","trump":"83430"},{"fips":"8071","total_vote":"6793","clinton":"2650","trump":"3710"},{"fips":"8073","total_vote":"2436","clinton":"409","trump":"1892"},{"fips":"8075","total_vote":"9722","clinton":"1851","trump":"7282"},{"fips":"8077","total_vote":"77654","clinton":"21729","trump":"49779"},{"fips":"8079","total_vote":"652","clinton":"237","trump":"344"},{"fips":"8081","total_vote":"6525","clinton":"874","trump":"5305"},{"fips":"8083","total_vote":"12858","clinton":"3973","trump":"7853"},{"fips":"8085","total_vote":"21186","clinton":"5466","trump":"14382"},{"fips":"8087","total_vote":"11960","clinton":"3151","trump":"8145"},{"fips":"8089","total_vote":"8452","clinton":"2943","trump":"4928"},{"fips":"8091","total_vote":"3310","clinton":"1697","trump":"1351"},{"fips":"8093","total_vote":"10417","clinton":"3421","trump":"6135"},{"fips":"8095","total_vote":"2332","clinton":"436","trump":"1791"},{"fips":"8097","total_vote":"10523","clinton":"7333","trump":"2550"},{"fips":"8099","total_vote":"5016","clinton":"1186","trump":"3531"},{"fips":"8101","total_vote":"78646","clinton":"35875","trump":"36265"},{"fips":"8103","total_vote":"3450","clinton":"436","trump":"2791"},{"fips":"8105","total_vote":"5534","clinton":"2001","trump":"3085"},{"fips":"8107","total_vote":"13986","clinton":"7600","trump":"5230"},{"fips":"8109","total_vote":"2835","clinton":"1417","trump":"1147"},{"fips":"8111","total_vote":"506","clinton":"265","trump":"215"},{"fips":"8113","total_vote":"4329","clinton":"2975","trump":"1033"},{"fips":"8115","total_vote":"1364","clinton":"267","trump":"1015"},{"fips":"8117","total_vote":"16174","clinton":"9557","trump":"5100"},{"fips":"8119","total_vote":"14444","clinton":"3603","trump":"9745"},{"fips":"8121","total_vote":"2733","clinton":"296","trump":"2299"},{"fips":"8123","total_vote":"135430","clinton":"46519","trump":"76651"},{"fips":"8125","total_vote":"4791","clinton":"726","trump":"3850"}]